{
  "description" : "rock",
  "draft" : false,
  "name" : "rock",
  "packageName" : "com.test1.rock",
  "tables" : [ {
    "catalog" : "rock",
    "columns" : [ {
      "columnValue" : {
        "type" : "user-defined",
        "insertable" : true,
        "updatable" : true,
        "defaultValue" : ""
      },
      "fieldName" : "id",
      "foreignKey" : false,
      "generatorType" : "identity",
      "generatorValue" : null,
      "javaType" : "integer",
      "length" : 0,
      "name" : "ID",
      "nullable" : false,
      "oldName" : "ID",
      "partOfAnyRelation" : false,
      "partOfForeignKey" : false,
      "partOfPrimaryKey" : true,
      "partOfUniqueKey" : true,
      "precision" : 10,
      "primaryKey" : true,
      "scale" : 0,
      "sqlType" : "number",
      "unique" : true
    } ],
    "constraints" : [ ],
    "entityName" : "Table1",
    "fullyQualifiedName" : "com.test1.rock.Table1",
    "name" : "TABLE1",
    "oldName" : "TABLE1",
    "primaryKey" : {
      "columns" : [ "ID" ],
      "composite" : false,
      "generator" : {
        "generatorType" : "identity",
        "generatorValue" : null
      },
      "name" : "PRIMARY",
      "virtual" : false
    },
    "relations" : [ ],
    "schema" : null,
    "type" : "TABLE"
  } ]
}